remoclip/__init__.py
remoclip/client_cli.py
remoclip/clipboard.py
remoclip/config.py
remoclip/db.py
remoclip/server_cli.py
remoclip-1.0.0.dist-info/WHEEL
remoclip-1.0.0.dist-info/entry_points.txt
remoclip-1.0.0.dist-info/METADATA
remoclip-1.0.0.dist-info/RECORD
