Metadata-Version: 2.4
Name: remoclip
Version: 1.0.0
Summary: Remote clipboard server and client CLI tools.
Keywords: clipboard
Author: Jeff Johnston
License-Expression: MIT
Classifier: Environment :: Console
Classifier: Intended Audience :: Developers
Classifier: Intended Audience :: System Administrators
Classifier: Programming Language :: Python :: 3.10
Classifier: Programming Language :: Python :: 3.11
Classifier: Programming Language :: Python :: 3.12
Classifier: Programming Language :: Python :: 3.13
Classifier: Programming Language :: Python :: 3.14
Requires-Dist: flask>=2.2
Requires-Dist: sqlalchemy>=1.4
Requires-Dist: pyyaml>=6.0
Requires-Dist: requests>=2.31
Requires-Dist: pyperclip>=1.8
Requires-Dist: werkzeug>=3.1.3
Requires-Python: >=3.10
Project-URL: Documentation, https://remoclip.newmatter.net
Project-URL: Issues, https://github.com/jeffjjohnston/remoclip/issues
Project-URL: Repository, https://github.com/jeffjjohnston/remoclip
